[
    {
        "name": "RD_KAFKA_RESP_ERR_UNKNOWN_TOPIC_ID",
        "ext_min": "6.0.3",
        "php_min": "7.0.0",
        "dependencies": [
            {
                "name": "librdkafka",
                "constraint": ">=2.3.0"
            }
        ]
    },
    {
        "name": "RD_KAFKA_RESP_ERR_UNRELEASED_INSTANCE_ID",
        "ext_min": "6.0.4",
        "php_min": "7.0.0",
        "dependencies": [
            {
                "name": "librdkafka",
                "constraint": ">=2.4.0"
            }
        ]
    },
    {
        "name": "RD_KAFKA_RESP_ERR_UNSUPPORTED_ASSIGNOR",
        "ext_min": "6.0.4",
        "php_min": "7.0.0",
        "dependencies": [
            {
                "name": "librdkafka",
                "constraint": ">=2.4.0"
            }
        ]
    },
    {
        "name": "RD_KAFKA_RESP_ERR_FENCED_MEMBER_EPOCH",
        "ext_min": "6.0.4",
        "php_min": "7.0.0",
        "dependencies": [
            {
                "name": "librdkafka",
                "constraint": ">=2.3.0"
            }
        ]
    },
    {
        "name": "RD_KAFKA_RESP_ERR_STALE_MEMBER_EPOCH",
        "ext_min": "6.0.4",
        "php_min": "7.0.0",
        "dependencies": [
            {
                "name": "librdkafka",
                "constraint": ">=2.3.0"
            }
        ]
    },
    {
        "name": "RD_KAFKA_RESP_ERR_UNKNOWN_SUBSCRIPTION_ID",
        "ext_min": "6.0.4",
        "php_min": "7.0.0",
        "dependencies": [
            {
                "name": "librdkafka",
                "constraint": ">=2.5.0"
            }
        ]
    },
    {
        "name": "RD_KAFKA_RESP_ERR_TELEMETRY_TOO_LARGE",
        "ext_min": "6.0.4",
        "php_min": "7.0.0",
        "dependencies": [
            {
                "name": "librdkafka",
                "constraint": ">=2.5.0"
            }
        ]
    },
    {
        "name": "RD_KAFKA_RESP_ERR_REBOOTSTRAP_REQUIRED",
        "ext_min": "6.0.4",
        "php_min": "7.0.0",
        "dependencies": [
            {
                "name": "librdkafka",
                "constraint": ">=2.9.0"
            }
        ]
    },
    {
        "name": "RD_KAFKA_RESP_ERR__LOG_TRUNCATION",
        "ext_min": "6.0.4",
        "php_min": "7.0.0",
        "dependencies": [
            {
                "name": "librdkafka",
                "constraint": ">=2.1.0"
            }
        ]
    },
    {
        "name": "RD_KAFKA_RESP_ERR__INVALID_DIFFERENT_RECORD",
        "ext_min": "6.0.4",
        "php_min": "7.0.0",
        "dependencies": [
            {
                "name": "librdkafka",
                "constraint": ">=2.4.0"
            }
        ]
    }
]
