[
    {
        "name": "openssl_cms_verify",
        "ext_min": "8.0.0",
        "php_min": "8.0.0alpha1"
    },
    {
        "name": "openssl_cms_encrypt",
        "ext_min": "8.0.0",
        "php_min": "8.0.0alpha1"
    },
    {
        "name": "openssl_cms_sign",
        "ext_min": "8.0.0",
        "php_min": "8.0.0alpha1"
    },
    {
        "name": "openssl_cms_decrypt",
        "ext_min": "8.0.0",
        "php_min": "8.0.0alpha1"
    },
    {
        "name": "openssl_cms_read",
        "ext_min": "8.0.0",
        "php_min": "8.0.0alpha1"
    }
]
