[
    {
        "name": "AppendIterator",
        "ext_min": "5.1.0",
        "ext_max": "",
        "php_min": "5.1.0",
        "php_max": ""
    },
    {
        "name": "BadFunctionCallException",
        "ext_min": "5.1.0",
        "ext_max": "",
        "php_min": "5.1.0",
        "php_max": ""
    },
    {
        "name": "BadMethodCallException",
        "ext_min": "5.1.0",
        "ext_max": "",
        "php_min": "5.1.0",
        "php_max": ""
    },
    {
        "name": "DomainException",
        "ext_min": "5.1.0",
        "ext_max": "",
        "php_min": "5.1.0",
        "php_max": ""
    },
    {
        "name": "EmptyIterator",
        "ext_min": "5.1.0",
        "ext_max": "",
        "php_min": "5.1.0",
        "php_max": ""
    },
    {
        "name": "FilterIterator",
        "ext_min": "5.1.0",
        "ext_max": "",
        "php_min": "5.1.0",
        "php_max": ""
    },
    {
        "name": "InfiniteIterator",
        "ext_min": "5.1.0",
        "ext_max": "",
        "php_min": "5.1.0",
        "php_max": ""
    },
    {
        "name": "InvalidArgumentException",
        "ext_min": "5.1.0",
        "ext_max": "",
        "php_min": "5.1.0",
        "php_max": ""
    },
    {
        "name": "IteratorIterator",
        "ext_min": "5.1.0",
        "ext_max": "",
        "php_min": "5.1.0",
        "php_max": ""
    },
    {
        "name": "LengthException",
        "ext_min": "5.1.0",
        "ext_max": "",
        "php_min": "5.1.0",
        "php_max": ""
    },
    {
        "name": "LimitIterator",
        "ext_min": "5.1.0",
        "ext_max": "",
        "php_min": "5.1.0",
        "php_max": ""
    },
    {
        "name": "LogicException",
        "ext_min": "5.1.0",
        "ext_max": "",
        "php_min": "5.1.0",
        "php_max": ""
    },
    {
        "name": "NoRewindIterator",
        "ext_min": "5.1.0",
        "ext_max": "",
        "php_min": "5.1.0",
        "php_max": ""
    },
    {
        "name": "OutOfBoundsException",
        "ext_min": "5.1.0",
        "ext_max": "",
        "php_min": "5.1.0",
        "php_max": ""
    },
    {
        "name": "OutOfRangeException",
        "ext_min": "5.1.0",
        "ext_max": "",
        "php_min": "5.1.0",
        "php_max": ""
    },
    {
        "name": "OverflowException",
        "ext_min": "5.1.0",
        "ext_max": "",
        "php_min": "5.1.0",
        "php_max": ""
    },
    {
        "name": "ParentIterator",
        "ext_min": "5.1.0",
        "ext_max": "",
        "php_min": "5.1.0",
        "php_max": ""
    },
    {
        "name": "RangeException",
        "ext_min": "5.1.0",
        "ext_max": "",
        "php_min": "5.1.0",
        "php_max": ""
    },
    {
        "name": "RecursiveArrayIterator",
        "ext_min": "5.1.0",
        "ext_max": "",
        "php_min": "5.1.0",
        "php_max": ""
    },
    {
        "name": "RecursiveCachingIterator",
        "ext_min": "5.1.0",
        "ext_max": "",
        "php_min": "5.1.0",
        "php_max": ""
    },
    {
        "name": "RecursiveDirectoryIterator",
        "ext_min": "5.1.2",
        "ext_max": "",
        "php_min": "5.1.2",
        "php_max": ""
    },
    {
        "name": "RecursiveFilterIterator",
        "ext_min": "5.1.0",
        "ext_max": "",
        "php_min": "5.1.0",
        "php_max": ""
    },
    {
        "name": "RecursiveIteratorIterator",
        "ext_min": "5.1.3",
        "ext_max": "",
        "php_min": "5.1.3",
        "php_max": ""
    },
    {
        "name": "RuntimeException",
        "ext_min": "5.1.0",
        "ext_max": "",
        "php_min": "5.1.0",
        "php_max": ""
    },
    {
        "name": "SimpleXMLIterator",
        "ext_min": "5.1.0",
        "ext_max": "5.2.17",
        "php_min": "5.1.0",
        "php_max": "5.2.17",
        "deprecated": "5.2.17"
    },
    {
        "name": "SplFileInfo",
        "ext_min": "5.1.2",
        "ext_max": "",
        "php_min": "5.1.2",
        "php_max": ""
    },
    {
        "name": "SplFileObject",
        "ext_min": "5.1.0",
        "ext_max": "",
        "php_min": "5.1.0",
        "php_max": ""
    },
    {
        "name": "SplObjectStorage",
        "ext_min": "5.1.0",
        "ext_max": "",
        "php_min": "5.1.0",
        "php_max": ""
    },
    {
        "name": "SplTempFileObject",
        "ext_min": "5.1.2",
        "ext_max": "",
        "php_min": "5.1.2",
        "php_max": ""
    },
    {
        "name": "UnderflowException",
        "ext_min": "5.1.0",
        "ext_max": "",
        "php_min": "5.1.0",
        "php_max": ""
    },
    {
        "name": "UnexpectedValueException",
        "ext_min": "5.1.0",
        "ext_max": "",
        "php_min": "5.1.0",
        "php_max": ""
    }
]