[
    {
        "name": "mysqli_begin_transaction",
        "ext_min": "5.5.0",
        "ext_max": "",
        "php_min": "5.5.0",
        "php_max": "",
        "parameters": "",
        "php_excludes": ""
    },
    {
        "name": "mysqli_release_savepoint",
        "ext_min": "5.5.0",
        "ext_max": "",
        "php_min": "5.5.0",
        "php_max": "",
        "parameters": "",
        "php_excludes": ""
    },
    {
        "name": "mysqli_savepoint",
        "ext_min": "5.5.0",
        "ext_max": "",
        "php_min": "5.5.0",
        "php_max": "",
        "parameters": "",
        "php_excludes": ""
    }
]
